burial_mounds/__init__.py
burial_mounds/__main__.py
burial_mounds/cli.py
burial_mounds/finetune.py
burial_mounds/hub.py
burial_mounds/model.py
burial_mounds/preprocess_mounds.py
burial_mounds/preprocess_xview.py
burial_mounds/utils.py
burial_mounds-0.2.0.dist-info/LICENSE
burial_mounds-0.2.0.dist-info/METADATA
burial_mounds-0.2.0.dist-info/WHEEL
burial_mounds-0.2.0.dist-info/RECORD
